ci_cmg_water_column_sonar_processing-25.7.2.dist-info/licenses/LICENSE-MIT
water_column_sonar_processing/__init__.py
water_column_sonar_processing/process.py
water_column_sonar_processing/aws/__init__.py
water_column_sonar_processing/aws/dynamodb_manager.py
water_column_sonar_processing/aws/s3_manager.py
water_column_sonar_processing/aws/s3fs_manager.py
water_column_sonar_processing/aws/sns_manager.py
water_column_sonar_processing/aws/sqs_manager.py
water_column_sonar_processing/cruise/__init__.py
water_column_sonar_processing/cruise/create_empty_zarr_store.py
water_column_sonar_processing/cruise/create_empty_zarr_store_level_3.py
water_column_sonar_processing/cruise/datatree_manager.py
water_column_sonar_processing/cruise/resample_regrid.py
water_column_sonar_processing/dataset/__init__.py
water_column_sonar_processing/dataset/dataset_manager.py
water_column_sonar_processing/dataset/feature_manager.py
water_column_sonar_processing/geometry/__init__.py
water_column_sonar_processing/geometry/elevation_manager.py
water_column_sonar_processing/geometry/geometry_manager.py
water_column_sonar_processing/geometry/line_simplification.py
water_column_sonar_processing/geometry/pmtile_generation.py
water_column_sonar_processing/index/__init__.py
water_column_sonar_processing/index/index_manager.py
water_column_sonar_processing/model/__init__.py
water_column_sonar_processing/model/zarr_manager.py
water_column_sonar_processing/processing/__init__.py
water_column_sonar_processing/processing/batch_downloader.py
water_column_sonar_processing/processing/raw_to_netcdf.py
water_column_sonar_processing/processing/raw_to_zarr.py
water_column_sonar_processing/utility/__init__.py
water_column_sonar_processing/utility/cleaner.py
water_column_sonar_processing/utility/constants.py
water_column_sonar_processing/utility/pipeline_status.py
water_column_sonar_processing/utility/timestamp.py
ci_cmg_water_column_sonar_processing-25.7.2.dist-info/METADATA
ci_cmg_water_column_sonar_processing-25.7.2.dist-info/WHEEL
ci_cmg_water_column_sonar_processing-25.7.2.dist-info/top_level.txt
ci_cmg_water_column_sonar_processing-25.7.2.dist-info/RECORD
