Metadata-Version: 2.4
Name: ci-cmg-water-column-sonar-processing
Version: 25.7.2
Summary: Processing tool for water column sonar data.
Author-email: Rudy Klucik <rudy.klucik@noaa.gov>
Maintainer-email: Rudy Klucik <rudy.klucik@noaa.gov>
License-Expression: MIT
Project-URL: Homepage, https://echo.fish
Project-URL: Repository, https://github.com/CI-CMG/water-column-sonar-processing
Project-URL: Issues, https://github.com/CI-CMG/water-column-sonar-processing/issues
Keywords: ocean,sonar,water column
Requires-Python: >=3.12
License-File: LICENSE-MIT
Requires-Dist: aiobotocore==2.21.1
Requires-Dist: aiohttp[speedups]
Requires-Dist: boto3==1.37.1
Requires-Dist: botocore==1.37.1
Requires-Dist: echopype==0.10.1
Requires-Dist: fiona==1.10.1
Requires-Dist: geopandas==1.1.1
Requires-Dist: mock==5.2.0
Requires-Dist: moto[all]==5.1.8
Requires-Dist: moto[server]==5.1.8
Requires-Dist: multidict==6.6.3
Requires-Dist: netcdf4==1.6.5
Requires-Dist: networkx==3.5.0
Requires-Dist: numcodecs==0.15.1
Requires-Dist: numpy==1.26.4
Requires-Dist: pandas==2.2.3
Requires-Dist: pooch==1.8.2
Requires-Dist: pyarrow==19.0.1
Requires-Dist: pykalman==0.10.1
Requires-Dist: python-dotenv==1.1.1
Requires-Dist: requests==2.32.4
Requires-Dist: s3fs==2025.5.1
Requires-Dist: scipy==1.15.1
Requires-Dist: setuptools==80.9.0
Requires-Dist: shapely==2.1.1
Requires-Dist: xarray==2025.7.0
Requires-Dist: xbatcher[tensorflow]==0.4.0
Requires-Dist: zarr==2.18.7
Provides-Extra: dev
Requires-Dist: bandit[toml]==1.8.0; extra == "dev"
Requires-Dist: bandit; extra == "dev"
Requires-Dist: black==25.1.0; extra == "dev"
Requires-Dist: build; extra == "dev"
Requires-Dist: isort; extra == "dev"
Requires-Dist: matplotlib; extra == "dev"
Requires-Dist: pooch==1.8.2; extra == "dev"
Requires-Dist: pre-commit; extra == "dev"
Requires-Dist: pyinstaller; extra == "dev"
Requires-Dist: pytest==8.3.5; extra == "dev"
Requires-Dist: ruff; extra == "dev"
Requires-Dist: tqdm; extra == "dev"
Requires-Dist: twine; extra == "dev"
Dynamic: license-file
